numba/__init__.py
numba/__main__.py
numba/_arraystruct.h
numba/_devicearray.cpython-310-darwin.so
numba/_devicearray.h
numba/_dispatcher.cpython-310-darwin.so
numba/_dynfunc.c
numba/_dynfunc.cpython-310-darwin.so
numba/_dynfuncmod.c
numba/_hashtable.h
numba/_helperlib.c
numba/_helperlib.cpython-310-darwin.so
numba/_helperlib.pyi
numba/_helpermod.c
numba/_lapack.c
numba/_numba_common.h
numba/_pymodule.h
numba/_random.c
numba/_typeof.h
numba/_unicodetype_db.h
numba/_version.py
numba/capsulethunk.h
numba/extending.py
numba/mathnames.h
numba/mviewbuf.c
numba/mviewbuf.cpython-310-darwin.so
numba/pythoncapi_compat.h
numba/runtests.py
numba/cext/__init__.py
numba/cext/cext.h
numba/cext/dictobject.c
numba/cext/dictobject.h
numba/cext/listobject.c
numba/cext/listobject.h
numba/cext/utils.c
numba/cloudpickle/__init__.py
numba/cloudpickle/cloudpickle.py
numba/cloudpickle/cloudpickle_fast.py
numba/core/__init__.py
numba/core/analysis.py
numba/core/base.py
numba/core/boxing.py
numba/core/bytecode.py
numba/core/byteflow.py
numba/core/caching.py
numba/core/callconv.py
numba/core/callwrapper.py
numba/core/ccallback.py
numba/core/cgutils.py
numba/core/codegen.py
numba/core/compiler.py
numba/core/compiler_lock.py
numba/core/compiler_machinery.py
numba/core/config.py
numba/core/consts.py
numba/core/controlflow.py
numba/core/cpu.py
numba/core/cpu_options.py
numba/core/debuginfo.py
numba/core/decorators.py
numba/core/descriptors.py
numba/core/dispatcher.py
numba/core/entrypoints.py
numba/core/environment.py
numba/core/errors.py
numba/core/event.py
numba/core/extending.py
numba/core/extending.pyi
numba/core/externals.py
numba/core/fastmathpass.py
numba/core/funcdesc.py
numba/core/generators.py
numba/core/imputils.py
numba/core/inline_closurecall.py
numba/core/interpreter.py
numba/core/intrinsics.py
numba/core/ir.py
numba/core/ir_utils.py
numba/core/itanium_mangler.py
numba/core/llvm_bindings.py
numba/core/lowering.py
numba/core/object_mode_passes.py
numba/core/optional.py
numba_forked_no_cuda-0.62.1.0.dist-info/LICENSE
numba_forked_no_cuda-0.62.1.0.dist-info/LICENSES.third-party
numba_forked_no_cuda-0.62.1.0.dist-info/METADATA
numba_forked_no_cuda-0.62.1.0.dist-info/WHEEL
numba_forked_no_cuda-0.62.1.0.dist-info/top_level.txt
numba_forked_no_cuda-0.62.1.0.dist-info/RECORD
