Metadata-Version: 2.1
Name: numba-forked-no-cuda
Version: 0.62.1.0
Summary: compiling Python code using LLVM
Home-page: https://numba.pydata.org
License: BSD
Classifier: Development Status :: 4 - Beta
Classifier: Intended Audience :: Developers
Classifier: License :: OSI Approved :: BSD License
Classifier: Operating System :: OS Independent
Classifier: Programming Language :: Python
Classifier: Programming Language :: Python :: 3
Classifier: Programming Language :: Python :: 3.10
Classifier: Programming Language :: Python :: 3.11
Classifier: Programming Language :: Python :: 3.12
Classifier: Programming Language :: Python :: 3.13
Classifier: Topic :: Software Development :: Compilers
Requires-Python: >=3.10
License-File: LICENSE
License-File: LICENSES.third-party
Requires-Dist: llvmlite<0.46,>=0.45.0dev0
Requires-Dist: numpy<2.4,>=1.22
